nx_logstats/__init__.py
nx_logstats/analysis.py
nx_logstats/cli.py
nx_logstats/parser.py
nx_logstats/reporter.py
nx_logstats-0.1.2.dist-info/METADATA
nx_logstats-0.1.2.dist-info/WHEEL
nx_logstats-0.1.2.dist-info/entry_points.txt
nx_logstats-0.1.2.dist-info/top_level.txt
nx_logstats-0.1.2.dist-info/RECORD
